read_font
