Metadata-Version: 1.0
Name: read-font
Version: 0.1.2
Summary: A tool that reads the bitmap representation of characters in fonts and outputs it in JSON format.
Home-page: https://github.com/bogdanm/read-font
Author: Bogdan Marinescu
Author-email: bogdan.marinescu@gmail.com
License: MIT
Platform: UNKNOWN
